GoGenji/GoGenji.py
GoGenji/Start.py
GoGenji/__init__.py
GoGenji/__main__.py
GoGenji/tushareUse/Helper.py
GoGenji/tushareUse/Save.py
GoGenji/tushareUse/__init__.py
GoGenji/tushareUse/addValue.py
GoGenji/tushareUse/tushareMain.py
GoGenji/wxpy/__init__.py
GoGenji/wxpy/__main__.py
GoGenji/wxpy/exceptions.py
GoGenji/wxpy/api/__init__.py
GoGenji/wxpy/api/bot.py
GoGenji/wxpy/api/chats/__init__.py
GoGenji/wxpy/api/chats/chat.py
GoGenji/wxpy/api/chats/chats.py
GoGenji/wxpy/api/chats/friend.py
GoGenji/wxpy/api/chats/group.py
GoGenji/wxpy/api/chats/groups.py
GoGenji/wxpy/api/chats/member.py
GoGenji/wxpy/api/chats/mp.py
GoGenji/wxpy/api/chats/user.py
GoGenji/wxpy/api/messages/__init__.py
GoGenji/wxpy/api/messages/message.py
GoGenji/wxpy/api/messages/message_config.py
GoGenji/wxpy/api/messages/message_configs.py
GoGenji/wxpy/api/messages/messages.py
GoGenji/wxpy/ext/__init__.py
GoGenji/wxpy/ext/logging_with_wechat.py
GoGenji/wxpy/ext/tuling.py
GoGenji/wxpy/utils/__init__.py
GoGenji/wxpy/utils/console.py
GoGenji/wxpy/utils/misc.py
GoGenji/wxpy/utils/tools.py
GoGenji-0.1.2.dist-info/DESCRIPTION.rst
GoGenji-0.1.2.dist-info/METADATA
GoGenji-0.1.2.dist-info/RECORD
GoGenji-0.1.2.dist-info/WHEEL
GoGenji-0.1.2.dist-info/entry_points.txt
GoGenji-0.1.2.dist-info/metadata.json
GoGenji-0.1.2.dist-info/top_level.txt
