Metadata-Version: 2.0
Name: GoGenji
Version: 0.1.2
Summary: GoGenji is a self helper, connecting the whole world within Wechat in peace
Home-page: https://github.com/KayShenA/PythonProjects
Author: Kay
Author-email: skyluckyrrb@126.com
License: MIT
Platform: UNKNOWN
Classifier: Development Status :: 4 - Beta
Classifier: License :: OSI Approved :: MIT License
Classifier: Programming Language :: Python :: 3
Classifier: Operating System :: OS Independent
Classifier: Topic :: Communications :: Chat
Classifier: Topic :: Utilities
Requires-Dist: itchat (==1.2.32)
Requires-Dist: matplotlib
Requires-Dist: pandas
Requires-Dist: python-docx
Requires-Dist: requests
Requires-Dist: seaborn
Requires-Dist: tushare
